textchart/__init__.py
textchart/textchart.py
textchart-0.0.3.dist-info/LICENSE
textchart-0.0.3.dist-info/METADATA
textchart-0.0.3.dist-info/WHEEL
textchart-0.0.3.dist-info/top_level.txt
textchart-0.0.3.dist-info/RECORD
