Metadata-Version: 2.1
Name: textchart
Version: 0.0.3
Summary: A simple text-only chart generator
Author-email: David Stein <textchart@stein.fyi>
License: Copyright 2022 David Stein        
Project-URL: Homepage, https://github.com/davidbstein/textchart
Project-URL: Bug Tracker, https://github.com/davidbstein/textchart/issues
Classifier: Programming Language :: Python :: 3
Classifier: License :: OSI Approved :: MIT License
Classifier: Operating System :: OS Independent
Requires-Python: >=3
License-File: LICENSE
